nonebot_plugin_atri/__init__.py
nonebot_plugin_atri/data.py
nonebot_plugin_atri/resources/text/atri.json
nonebot_plugin_atri/resources/voice/.......不知不觉，清洗液从眼睛里出来了.mp3
nonebot_plugin_atri/resources/voice/.......你想在这里做什么？.mp3
nonebot_plugin_atri/resources/voice/.......出来了.mp3
nonebot_plugin_atri/resources/voice/.......因为会觉得，我并不是一个人.mp3
nonebot_plugin_atri/resources/voice/.......小镇，真暗呢.mp3
nonebot_plugin_atri/resources/voice/.......我为了夏生先生行动需要理由吗.mp3
nonebot_plugin_atri/resources/voice/.......我呢，其实有点羨慕她呢.mp3
nonebot_plugin_atri/resources/voice/.......拿你没办法呀，原谅你了。等我社团活动结束.mp3
nonebot_plugin_atri/resources/voice/.......非常感谢。但我没法回复你的喜欢.mp3
nonebot_plugin_atri/resources/voice/......一个人睡的话，就有种再也起不来的感觉.mp3
nonebot_plugin_atri/resources/voice/......不愧夏生先生，华丽的推理。我都快迷上了.mp3
nonebot_plugin_atri/resources/voice/......不能理解。有什么区别呢.mp3
nonebot_plugin_atri/resources/voice/......为什么呢？明明非常非常难受的.mp3
nonebot_plugin_atri/resources/voice/......为什么带我来这里？.mp3
nonebot_plugin_atri/resources/voice/......主人看我的时候，一脸惊慌失措的样子.mp3
nonebot_plugin_atri/resources/voice/......也就是说，我现在正在高兴吗.mp3
nonebot_plugin_atri/resources/voice/......但是，夏生先生想这样的的话，那我也只能勉为其难的配合了.mp3
nonebot_plugin_atri/resources/voice/......但是，该怎么高兴呢，我也是新手.mp3
nonebot_plugin_atri/resources/voice/......保护是我的职责。夏生先生就这样被我保护吧.mp3
"nonebot_plugin_atri/resources/voice/......其实,我是某国秘密制造的战斗机器人.mp3"
nonebot_plugin_atri/resources/voice/......其实，我是某国秘密制造的战斗机器人.mp3
nonebot_plugin_atri/resources/voice/......只要不坏掉就能一直待在夏生先生身边，这是多大的特权啊，明明那么低性能.mp3
nonebot_plugin_atri/resources/voice/......合理，因为，都已经确认过喜欢了.mp3
nonebot_plugin_atri/resources/voice/......和机器人谈恋爱，夏生先生也真是怪呢.mp3
nonebot_plugin_atri/resources/voice/......哎呀没错，这是极度机密事项，请不要外传.mp3
nonebot_plugin_atri/resources/voice/......啊.mp3
nonebot_plugin_atri/resources/voice/......嗅嗅。的确这味道是烧焦了.mp3
nonebot_plugin_atri/resources/voice/......嗯？.mp3
nonebot_plugin_atri/resources/voice/......因为担心夏生先生像刚刚那样跌倒，就选择在这等了.mp3
nonebot_plugin_atri/resources/voice/......夏生先生不靠帮助，只靠一条腿去采了果子吗.mp3
nonebot_plugin_atri-0.0.4.dist-info/LICENSE
nonebot_plugin_atri-0.0.4.dist-info/WHEEL
nonebot_plugin_atri-0.0.4.dist-info/METADATA
nonebot_plugin_atri-0.0.4.dist-info/RECORD
